UsefulHelper/__init__.py
UsefulHelper/cli.py
UsefulHelper/manager.py
UsefulHelper/packer.py
UsefulHelper/test.py
UsefulHelper/Project/__init__.py
UsefulHelper/Project/App/__init__.py
UsefulHelper/Project/SQL/SQLite.py
UsefulHelper/Project/SQL/UNKnownDB.py
UsefulHelper/Project/SQL/__init__.py
UsefulHelper/Project/Temple/__init__.py
UsefulHelper/Tools/__init__.py
UsefulHelper/Tools/search.py
UsefulHelper/Tools/tree.py
UsefulHelper-1.7.5.data/scripts/start.py
UsefulHelper-1.7.5.dist-info/METADATA
UsefulHelper-1.7.5.dist-info/WHEEL
UsefulHelper-1.7.5.dist-info/top_level.txt
UsefulHelper-1.7.5.dist-info/RECORD
