Metadata-Version: 2.1
Name: UsefulHelper
Version: 1.7.5
Summary: Some useful tools
Home-page: https://github.com/CleverCreater/UsefulHelper
Author: CleaverCreator
Author-email: liuhanbo333@icloud.com
License: MIT
Platform: Linux
Requires-Python: >=3.9
Requires-Dist: PyQt5
